volumez_client/__init__.py
volumez_client/api/__init__.py
volumez_client/api/alerts/__init__.py
volumez_client/api/alerts/alert_acknowledge.py
volumez_client/api/alerts/alerts_list.py
volumez_client/api/amp/__init__.py
volumez_client/api/amp/get_subscription.py
volumez_client/api/associations/__init__.py
volumez_client/api/associations/association_create.py
volumez_client/api/associations/association_delete.py
volumez_client/api/associations/association_modify.py
volumez_client/api/associations/associations_list.py
volumez_client/api/attachments/__init__.py
volumez_client/api/attachments/attachment_create.py
volumez_client/api/attachments/attachment_delete.py
volumez_client/api/attachments/attachment_get.py
volumez_client/api/attachments/attachment_modify.py
volumez_client/api/attachments/attachments_list.py
volumez_client/api/attachments/attachments_list_all.py
volumez_client/api/attachments/attachments_list_for_volume.py
volumez_client/api/auto_provision_volumes/__init__.py
volumez_client/api/auto_provision_volumes/auto_provision_volumes.py
volumez_client/api/capacity_groups/__init__.py
volumez_client/api/capacity_groups/capacity_group_get.py
volumez_client/api/connectivities/__init__.py
volumez_client/api/connectivities/connectivities_list.py
volumez_client/api/connectivities/connectivity_create.py
volumez_client/api/connectivities/connectivity_delete.py
volumez_client/api/connectivities/connectivity_get.py
volumez_client/api/connectivities/connectivity_modify.py
volumez_client/api/exports/__init__.py
volumez_client/api/exports/export_create.py
volumez_client/api/exports/export_delete.py
volumez_client/api/exports/export_modify.py
volumez_client/api/exports/exports_list.py
volumez_client/api/jobs/__init__.py
volumez_client/api/jobs/job_delete.py
volumez_client/api/jobs/job_get.py
volumez_client/api/jobs/job_resume_suspend.py
volumez_client/api/jobs/jobs_list.py
volumez_client/api/media/__init__.py
volumez_client/api/media/media_assign.py
volumez_client-1.0.0.dist-info/METADATA
volumez_client-1.0.0.dist-info/WHEEL
volumez_client-1.0.0.dist-info/RECORD
